evobandits-0.0.6.dist-info/METADATA
evobandits-0.0.6.dist-info/WHEEL
evobandits/__init__.py
evobandits/evobandits.cp312-win_amd64.pyd
evobandits/logging.py
evobandits/params/README.md
evobandits/params/__init__.py
evobandits/params/base_param.py
evobandits/params/categorical_param.py
evobandits/params/float_param.py
evobandits/params/int_param.py
evobandits/py.typed
evobandits/search.py
evobandits/study/__init__.py
evobandits/study/study.py
evobandits-0.0.6.dist-info/RECORD
