Metadata-Version: 2.4
Name: evobandits
Version: 0.0.6
Classifier: Programming Language :: Rust
Classifier: Programming Language :: Python :: Implementation :: CPython
Classifier: Programming Language :: Python :: Implementation :: PyPy
Classifier: Operating System :: Unix
Classifier: Operating System :: Microsoft :: Windows
Classifier: Operating System :: MacOS
Classifier: Intended Audience :: Developers
Classifier: Intended Audience :: Science/Research
Requires-Dist: scikit-learn ; extra == 'sklearn'
Requires-Dist: pytest ; extra == 'test'
Requires-Dist: scikit-learn ; extra == 'test'
Requires-Dist: coverage[toml] ; extra == 'test'
Provides-Extra: sklearn
Provides-Extra: test
Summary: Optimization algorithm combining genetic algorithms and multi-armed bandits for stochastic problems
Keywords: optimization,evolutionary computation,genetic algorithms,multi-armed bandits,stochastic problems,machine learning,reinforcement learning
Author: Deniz Preil, Felix Würmseher, Jonathan Laib, Timo Kühne
Requires-Python: >=3.10
Project-URL: Documentation, https://evobandits.github.io/EvoBandits/
Project-URL: Repository, https://github.com/EvoBandits/EvoBandits
